setup.py
mblock/__init__.py
mblock-0.0.2.dist-info/METADATA
mblock-0.0.2.dist-info/WHEEL
mblock-0.0.2.dist-info/top_level.txt
mblock-0.0.2.dist-info/RECORD
